Metadata-Version: 1.0
Name: speaklib
Version: 0.0.1
Summary: 为程序输出表达进行优化，比如AI说话、逐字输出。
Home-page: https://code.xueersi.com
Author: Ruoyu Wang
Author-email: UNKNOWN
License: UNKNOWN
Platform: UNKNOWN
